{"_default": {"1": {"name": "KUMITE", "artist": "Salmo", "album": "FLOP", "date": "1011-10-11", "n": 6}, "2": {"name": "SOGNI D'ORO", "artist": "Lazza", "album": "SIRIO", "date": "1011-10-11", "n": 3}, "3": {"name": "Senza (feat. En?gma, Slait)", "artist": "Salmo", "album": "Death USB", "date": "1011-10-11", "n": 1}, "4": {"name": "Angelina Jolie", "artist": "Bresh", "album": "Angelina Jolie", "date": "1011-10-11", "n": 1}, "5": {"name": "CASA", "artist": "Neima Ezza", "album": "CASA", "date": "1011-10-11", "n": 1}, "6": {"name": "s!r! (feat. Lazza & Sfera Ebbasta)", "artist": "thasup", "album": "s!r! (feat. Lazza & Sfera Ebbasta)", "date": "1011-10-11", "n": 2}, "7": {"name": "LEI (feat. Rondodasosa)", "artist": "Neima Ezza", "album": "Gi\u00f9", "date": "1011-10-11", "n": 1}, "8": {"name": "Morto Mai (Piano Solo)", "artist": "Lazza", "album": "Re Mida (Aurum)", "date": "1011-10-11", "n": 2}, "9": {"name": "Non Fare Cos\u00ec", "artist": "Capo Plaza", "album": "PLAZA", "date": "1011-10-11", "n": 3}, "10": {"name": "A Nightingale Sang In Berkeley Square", "artist": "Southside Players", "album": "A Nightingale Sang In Berkeley Square", "date": "1011-10-11", "n": 2}, "11": {"name": "Cirano", "artist": "Francesco Guccini", "album": "D'Amore Di Morte E Di Altre Sciocchezze", "date": "2022-10-12", "n": 1}, "12": {"name": "Lo spazzacamino", "artist": "DJ Myke", "album": "Hocus pocus", "date": "2022-10-12", "n": 1}, "13": {"name": "Un Bacio sulla Fronte (feat. Silent Bob)", "artist": "En?gma", "album": "TOTEM (Ultimate Edition)", "date": "2022-10-15", "n": 1}, "14": {"name": "Canzone All'uscita", "artist": "Caparezza", "album": "Museica", "date": "2022-10-15", "n": 1}, "15": {"name": "Mai una gioia", "artist": "Shade", "album": "Mirabilansia", "date": "2022-10-14", "n": 1}, "16": {"name": "Te lo prometto", "artist": "Il Tre", "album": "ALI", "date": "2022-10-14", "n": 2}, "17": {"name": "Mama quanto grezi", "artist": "Herman Medrano", "album": "Mama quanto grezi", "date": "2022-10-14", "n": 1}, "18": {"name": "Vida", "artist": "Ghali", "album": "Album", "date": "2022-10-12", "n": 1}, "19": {"name": "Bimbe (Holla)", "artist": "Various Artists", "album": "Bimbe (Holla)", "date": "2022-10-12", "n": 1}, "20": {"name": "Amici", "artist": "Massimo Pericolo", "album": "Scialla Semper", "date": "2022-10-12", "n": 1}, "21": {"name": "Asylum (feat. En?gma)", "artist": "BLOODY VINYL", "album": "BV2", "date": "2022-10-12", "n": 2}, "22": {"name": "B.U.F.", "artist": "Nerone", "album": "B.U.F.", "date": "2022-10-12", "n": 1}, "23": {"name": "Libellule - prod. CRVEL & STABBER", "artist": "Nitro", "album": "GarbAge", "date": "2022-10-12", "n": 2}, "24": {"name": "Bimbo Grande", "artist": "Limon Willis", "album": "Bimbo Grande", "date": "2022-10-12", "n": 1}, "25": {"name": "Un sec", "artist": "Nerone", "album": "MAXTAPE", "date": "2022-10-12", "n": 1}, "26": {"name": "GHIGLIOTTINA - feat. Noyz Narcos", "artist": "Salmo", "album": "FLOP", "date": "2022-10-12", "n": 1}, "27": {"name": "Farabutto (feat. Madame)", "artist": "Tredici Pietro", "album": "Assurdo", "date": "2022-10-12", "n": 2}, "28": {"name": "Trabajo", "artist": "Pepito Rella", "album": "Masquereal", "date": "2022-10-12", "n": 1}, "29": {"name": "Cabernet Boys", "artist": "Herman Medrano", "album": "Mediamente Mona", "date": "2022-10-12", "n": 1}, "30": {"name": "Krav Maga", "artist": "En?gma", "album": "Shardana", "date": "2022-10-17", "n": 2}, "31": {"name": "Lewandowski VII", "artist": "Ernia", "album": "Gemelli (ascendente Milano)", "date": "2022-10-17", "n": 1}, "32": {"name": "Boh, non so", "artist": "Shade", "album": "Truman (Sanremo Edition)", "date": "2022-10-17", "n": 1}, "33": {"name": "Affogare.", "artist": "En?gma", "album": "Affogare.", "date": "2022-10-16", "n": 1}, "34": {"name": "Harley Quinn", "artist": "Highsnob", "album": "Harley Quinn", "date": "2022-10-17", "n": 1}, "35": {"name": "Intro", "artist": "Duplici", "album": "Schiena Contro Schiena", "date": "2022-10-17", "n": 1}, "36": {"name": "Emme I", "artist": "Nerone", "album": "Entertainer", "date": "2022-10-17", "n": 1}, "37": {"name": "Ready Or Not", "artist": "Various Artists", "album": "The Voice Of Italy 2019 - The Best Of Blind Auditions", "date": "2022-10-17", "n": 1}, "38": {"name": "Ben Ten", "artist": "Highsnob", "album": "Ben Ten", "date": "2022-10-17", "n": 1}, "39": {"name": "Portami con Te.", "artist": "En?gma", "album": "Portami con Te.", "date": "2022-10-17", "n": 1}, "40": {"name": "Bravi ragazzi", "artist": "I Melt", "album": "Bravi ragazzi", "date": "2022-10-17", "n": 1}, "41": {"name": "Ehy Boy", "artist": "Ernia", "album": "Come Uccidere Un Usignolo (67 Edition)", "date": "2022-10-19", "n": 1}, "42": {"name": "Animalz - prod. Strage", "artist": "Nitro", "album": "GarbAge Evilution", "date": "2022-10-19", "n": 1}, "43": {"name": "3 DI CUORI (feat. Lazza)", "artist": "ANNA", "album": "3 DI CUORI (feat. Lazza)", "date": "2022-10-19", "n": 1}, "44": {"name": "FIORI", "artist": "Giaime", "album": "FIORI", "date": "2022-10-19", "n": 1}, "45": {"name": "Vecchia mia (feat. Mezzosangue & En?gma)", "artist": "BLOODY VINYL", "album": "BV2", "date": "2022-10-19", "n": 1}, "46": {"name": "Oh Yes (freestyle)", "artist": "Nerone", "album": "MAXTAPE", "date": "2022-10-19", "n": 1}, "47": {"name": "Olimpiade", "artist": "En?gma", "album": "Rebus", "date": "2022-10-19", "n": 1}, "48": {"name": "Vedo", "artist": "Albert", "album": "Orme", "date": "2022-10-19", "n": 1}, "49": {"name": "Bocca di rosa", "artist": "Albert", "album": "Alterego", "date": "2022-10-19", "n": 1}, "50": {"name": "Rapper al rovescio", "artist": "Rancore", "album": "La morte di rinquore (14/2/08)", "date": "2022-10-19", "n": 1}, "51": {"name": "L'Uomo Che Premette", "artist": "Caparezza", "album": "Prisoner 709", "date": "2022-10-19", "n": 1}, "52": {"name": "Campione Dei Novanta", "artist": "Caparezza", "album": "Exuvia", "date": "2022-10-19", "n": 1}, "53": {"name": "Kitaro", "artist": "Caparezza", "album": "Museica", "date": "2022-10-19", "n": 1}, "54": {"name": "Timidamente io - Coi Violini", "artist": "Ruggero De I Timidi", "album": "Frutto proibito", "date": "2022-10-19", "n": 1}, "55": {"name": "Il Testo Che Avrei Voluto Scrivere", "artist": "Caparezza", "album": "Prisoner 709", "date": "2022-10-19", "n": 1}, "56": {"name": "Cani sciolti", "artist": "Sangue Misto", "album": "SXM", "date": "2022-10-20", "n": 1}, "57": {"name": "QQQ", "artist": "Ernia", "album": "68", "date": "2022-10-20", "n": 1}, "58": {"name": "Nuvole & Cupole", "artist": "En?gma", "album": "Nuvole & Cupole", "date": "2022-10-20", "n": 1}, "59": {"name": "Frigobar", "artist": "Franco126", "album": "Stanza Singola", "date": "2022-10-20", "n": 1}, "60": {"name": "La Cenerentola del Ring", "artist": "En?gma", "album": "Shardana", "date": "2022-10-20", "n": 1}, "61": {"name": "Cowboy - feat. Tedua", "artist": "Emis Killa", "album": "17", "date": "2022-10-20", "n": 1}, "62": {"name": "MADAME - L'anima (feat. Madame)", "artist": "Marracash", "album": "Persona", "date": "2022-10-20", "n": 1}, "63": {"name": "Testa Calda", "artist": "Limon Willis", "album": "Leader", "date": "2022-10-20", "n": 1}, "64": {"name": "BARSMAGEDDON - prod. Low Kidd", "artist": "Nitro", "album": "GarbAge Evilution", "date": "2022-10-20", "n": 1}}}